denari/__init__.py
denari/analytica.py
denari/tributum.py
denari/Tax Tables/__init__.py
denari/Tax Tables/uk/__init__.py
denari/Tax Tables/uk/2021-2022/__init__.py
denari/Tax Tables/uk/2021-2022/bands_corporate_ni.csv
denari/Tax Tables/uk/2021-2022/bands_employee_ni.csv
denari/Tax Tables/uk/2021-2022/rates_dividend.csv
denari/Tax Tables/uk/2021-2022/single_threshold_allowance_change.csv
denari/Tax Tables/uk/2021-2022/single_threshold_dividends_tax_free.csv
denari/Tax Tables/uk/2021-2022/thresholds_corporate_national_insurance.csv
denari/Tax Tables/uk/2021-2022/thresholds_corporation_tax.csv
denari/Tax Tables/uk/2021-2022/thresholds_employee_national_insurance.csv
denari/Tax Tables/uk/2021-2022/thresholds_income_tax.csv
denari/Tax Tables/uk/2021-2022/thresholds_student_loans.csv
denari/Tax Tables/uk/2021-2022/__pycache__/__init__.cpython-39.pyc
denari/Tax Tables/uk/2022-2023/__init__.py
denari/Tax Tables/uk/2022-2023/bands_corporate_ni.csv
denari/Tax Tables/uk/2022-2023/bands_employee_ni.csv
denari/Tax Tables/uk/2022-2023/rates_dividend.csv
denari/Tax Tables/uk/2022-2023/single_threshold_allowance_change.csv
denari/Tax Tables/uk/2022-2023/single_threshold_dividends_tax_free.csv
denari/Tax Tables/uk/2022-2023/thresholds_corporate_national_insurance.csv
denari/Tax Tables/uk/2022-2023/thresholds_corporation_tax.csv
denari/Tax Tables/uk/2022-2023/thresholds_employee_national_insurance.csv
denari/Tax Tables/uk/2022-2023/thresholds_income_tax.csv
denari/Tax Tables/uk/2022-2023/thresholds_student_loans.csv
denari/Tax Tables/uk/2022-2023/__pycache__/__init__.cpython-39.pyc
denari/Tax Tables/uk/2023-2024/__init__.py
denari/Tax Tables/uk/2023-2024/bands_corporate_ni.csv
denari/Tax Tables/uk/2023-2024/bands_employee_ni.csv
denari/Tax Tables/uk/2023-2024/rates_dividend.csv
denari/Tax Tables/uk/2023-2024/single_threshold_allowance_change.csv
denari/Tax Tables/uk/2023-2024/single_threshold_dividends_tax_free.csv
denari-1.0.48.dist-info/LICENCE
denari-1.0.48.dist-info/METADATA
denari-1.0.48.dist-info/WHEEL
denari-1.0.48.dist-info/top_level.txt
denari-1.0.48.dist-info/RECORD
