Metadata-Version: 2.1
Name: denari
Version: 1.0.48
Summary: DenariAnalytics OpenSource Business Analytics (analytica) and Tax Optimisation Tools (tributum)
Author: Fadil Karim
Author-email: fid_kk@proton.me
License-File: LICENCE
Requires-Dist: pandas
Requires-Dist: numpy
Requires-Dist: plotly
Requires-Dist: dash
